devpi_discord/__init__.py
devpi_discord/discord_api.py
devpi_discord/entrypoint.py
devpi_discord-0.0.2.dist-info/LICENSE.txt
devpi_discord-0.0.2.dist-info/METADATA
devpi_discord-0.0.2.dist-info/WHEEL
devpi_discord-0.0.2.dist-info/entry_points.txt
devpi_discord-0.0.2.dist-info/top_level.txt
devpi_discord-0.0.2.dist-info/RECORD
