Metadata-Version: 2.1
Name: devpi-discord
Version: 0.0.2
Summary: Devpi plugin for sending Discord notifications
Home-page: http://github.com/turbokadi/devpi-discord
Author: MoJoh
Author-email: cryptoweirdo@protonmail.com
License: MIT
Keywords: devpi discord notification
Platform: any
Classifier: Development Status :: 3 - Alpha
Classifier: Intended Audience :: System Administrators
Classifier: License :: OSI Approved :: MIT License
Classifier: Topic :: Software Development :: Libraries :: Python Modules
Classifier: Topic :: Internet
License-File: LICENSE.txt
Requires-Dist: devpi-server (>=4.0.0)
Requires-Dist: requests (>=2.28.1)
